graphs_AustynGriegoMSU/__init__.py
graphs_AustynGriegoMSU/heapq.py
graphs_AustynGriegoMSU/sp.py
graphs_austyngriegomsu-0.0.3.dist-info/METADATA
graphs_austyngriegomsu-0.0.3.dist-info/WHEEL
graphs_austyngriegomsu-0.0.3.dist-info/RECORD
