Metadata-Version: 2.4
Name: graphs_AustynGriegoMSU
Version: 0.0.3
Summary: Python library that implements Dijkstra's shortest path algorithm. 
Project-URL: Homepage, https://github.com/AustynGriegoMSU/graphs_AustynGriegoMSU
Project-URL: Bug Tracker, https://github.com/AustynGriegoMSU/graphs_AustynGriegoMSU/issues
Author-email: Austyn Griego <agriego4@msudenver.edu>
Classifier: License :: OSI Approved :: MIT License
Classifier: Operating System :: OS Independent
Classifier: Programming Language :: Python :: 3
Requires-Python: >=3.7
